{
  "base_price": 3750,
  "beamstation_catalog_url": "https://beamstation.com/datasets",
  "beamstation_origin": "https://beamstation.com",
  "category_group_name": "Restaurants",
  "config_category": "census",
  "config_description": "Regional restaurant data for the Baton Rouge (Metro), Louisiana metropolitan area, spanning Baton Rouge. Spans multiple municipalities within a mid-size metropolitan dining market. Filtered by the Restaurants category group with business profiles, sentiment data, review trends, and competitive benchmarks. Refreshed weekly.",
  "config_name": "All Restaurants in Baton Rouge (Metro), Louisiana, US",
  "export_job_id": "e1ecb53b-608a-4177-be0a-185cb3bb1fdc",
  "github_org": "Beamstation-Datasets",
  "id_short": 671204,
  "location_name": "Baton Rouge, LA",
  "location_type": "metro",
  "repo_name": "all-restaurants-in-baton-rouge-metro-louisiana-us-sample-671204",
  "sample_b2_path": "b2-export:BeamStation-ExportFiles/671204/beamstation_671204_restaurants-us-batonrougela_SAMPLE_DIST.csv",
  "sample_pct": 9.97,
  "sample_records": 197,
  "sample_sha256": "40426c917bca33f36d9fc2ae4f06954451c09435db1a13032f053a6284b3f9fb",
  "sample_size_bytes": 722008,
  "total_records": 1975,
  "updated_at": "2026-04-14T19:29:48.290016+00:00"
}